{
  "care_weight": 0.3,
  "forage_weight": 0.5,
  "self_weight": 0.3,
  "num_runs": 15,
  "mother_survival_rate_mean": 0.0,
  "mother_survival_rate_sd": 0.0,
  "child_survival_rate_mean": 0.0,
  "child_survival_rate_sd": 0.0,
  "mean_mother_energy_mean": 0.4225517778298213,
  "mean_mother_energy_sd": 0.038217835977323165,
  "final_mother_energy_mean": 0.0,
  "final_mother_energy_sd": 0.0,
  "mean_child_hunger_mean": 0.47429992252579567,
  "mean_child_hunger_sd": 0.06731535718938503,
  "mean_child_distress_mean": 0.44584739418547936,
  "mean_child_distress_sd": 0.07132814786407987,
  "care_rate_mean": 0.21128751482840122,
  "care_rate_sd": 0.015299598776273902,
  "passes_threshold": 0,
  "selection_status": "fallback_no_threshold_pass",
  "selected": 1,
  "selection_rule": "Lowest care_weight with mother_surv\u22650.8 AND child_surv\u22650.8 AND care_rate>0.05; tie-break: highest mean_mother_energy."
}