[
  {
    "tick": 200,
    "avg_care_weight": 0.8002796626302894,
    "var_care_weight": 0.00020696949688038971,
    "avg_forage_weight": 0.9999333331907666,
    "avg_self_weight": 0.47855816682535823,
    "avg_generation": 0.5555555555555556,
    "max_generation": 1,
    "n_mothers": 72
  },
  {
    "tick": 400,
    "avg_care_weight": 0.799375090121405,
    "var_care_weight": 0.00034446371949835747,
    "avg_forage_weight": 0.9957915612509582,
    "avg_self_weight": 0.4666945518371533,
    "avg_generation": 1.3943661971830985,
    "max_generation": 3,
    "n_mothers": 71
  },
  {
    "tick": 600,
    "avg_care_weight": 0.7983812068162173,
    "var_care_weight": 0.0005965836846916602,
    "avg_forage_weight": 0.9916000245452234,
    "avg_self_weight": 0.5499850589905783,
    "avg_generation": 3.6,
    "max_generation": 5,
    "n_mothers": 35
  },
  {
    "tick": 800,
    "avg_care_weight": 0.800250680581839,
    "var_care_weight": 0.0008015704039630448,
    "avg_forage_weight": 0.9941641188999033,
    "avg_self_weight": 0.5120232615792439,
    "avg_generation": 5.870967741935484,
    "max_generation": 7,
    "n_mothers": 31
  },
  {
    "tick": 1000,
    "avg_care_weight": 0.8010439583018849,
    "var_care_weight": 0.0009242864567380861,
    "avg_forage_weight": 0.9904705907924556,
    "avg_self_weight": 0.5233127364437608,
    "avg_generation": 7.757575757575758,
    "max_generation": 9,
    "n_mothers": 33
  },
  {
    "tick": 1200,
    "avg_care_weight": 0.8064978934863513,
    "var_care_weight": 0.002231370441914069,
    "avg_forage_weight": 0.9830974062874891,
    "avg_self_weight": 0.46327358433758276,
    "avg_generation": 9.857142857142858,
    "max_generation": 11,
    "n_mothers": 35
  },
  {
    "tick": 1400,
    "avg_care_weight": 0.8116720353537411,
    "var_care_weight": 0.003229813169167725,
    "avg_forage_weight": 0.9847642156497297,
    "avg_self_weight": 0.4996611106008475,
    "avg_generation": 11.89655172413793,
    "max_generation": 13,
    "n_mothers": 29
  },
  {
    "tick": 1600,
    "avg_care_weight": 0.8031612328841763,
    "var_care_weight": 0.003179764481358466,
    "avg_forage_weight": 0.9849871663876637,
    "avg_self_weight": 0.511299026380985,
    "avg_generation": 13.964285714285714,
    "max_generation": 15,
    "n_mothers": 28
  },
  {
    "tick": 1800,
    "avg_care_weight": 0.803899858376774,
    "var_care_weight": 0.0033159568468553078,
    "avg_forage_weight": 0.9856332621246134,
    "avg_self_weight": 0.5226542510414429,
    "avg_generation": 16.074074074074073,
    "max_generation": 17,
    "n_mothers": 27
  },
  {
    "tick": 2000,
    "avg_care_weight": 0.8071035163757251,
    "var_care_weight": 0.004118032611202041,
    "avg_forage_weight": 0.9844040496623864,
    "avg_self_weight": 0.5257795927282527,
    "avg_generation": 18.076923076923077,
    "max_generation": 19,
    "n_mothers": 26
  },
  {
    "tick": 2200,
    "avg_care_weight": 0.8037517696724008,
    "var_care_weight": 0.004290403133976692,
    "avg_forage_weight": 0.9857476000359581,
    "avg_self_weight": 0.5149402359516152,
    "avg_generation": 20.0,
    "max_generation": 21,
    "n_mothers": 28
  },
  {
    "tick": 2400,
    "avg_care_weight": 0.8015931457399137,
    "var_care_weight": 0.005060303841610466,
    "avg_forage_weight": 0.9866631478768775,
    "avg_self_weight": 0.5275717058219113,
    "avg_generation": 21.93103448275862,
    "max_generation": 23,
    "n_mothers": 29
  },
  {
    "tick": 2600,
    "avg_care_weight": 0.8033622381533062,
    "var_care_weight": 0.005879462799562744,
    "avg_forage_weight": 0.9741883574224095,
    "avg_self_weight": 0.507664719825003,
    "avg_generation": 24.0,
    "max_generation": 25,
    "n_mothers": 28
  },
  {
    "tick": 2800,
    "avg_care_weight": 0.8054605046361852,
    "var_care_weight": 0.006821658818869252,
    "avg_forage_weight": 0.9650459461527428,
    "avg_self_weight": 0.5077870665795173,
    "avg_generation": 26.0,
    "max_generation": 27,
    "n_mothers": 28
  },
  {
    "tick": 3000,
    "avg_care_weight": 0.8065893622032289,
    "var_care_weight": 0.006637716001863885,
    "avg_forage_weight": 0.9599592541094443,
    "avg_self_weight": 0.5071117639684977,
    "avg_generation": 28.0,
    "max_generation": 29,
    "n_mothers": 28
  },
  {
    "tick": 3200,
    "avg_care_weight": 0.8092882473328354,
    "var_care_weight": 0.0076561618176081685,
    "avg_forage_weight": 0.952177510274138,
    "avg_self_weight": 0.5081393281387759,
    "avg_generation": 30.037037037037038,
    "max_generation": 31,
    "n_mothers": 27
  },
  {
    "tick": 3400,
    "avg_care_weight": 0.8024614650602867,
    "var_care_weight": 0.007241098967525864,
    "avg_forage_weight": 0.9535319799779649,
    "avg_self_weight": 0.533460074765658,
    "avg_generation": 31.933333333333334,
    "max_generation": 33,
    "n_mothers": 30
  },
  {
    "tick": 3600,
    "avg_care_weight": 0.8039000213043134,
    "var_care_weight": 0.008007733762883077,
    "avg_forage_weight": 0.9501364229927017,
    "avg_self_weight": 0.5147378497002303,
    "avg_generation": 34.0,
    "max_generation": 35,
    "n_mothers": 28
  },
  {
    "tick": 3800,
    "avg_care_weight": 0.8022538687085,
    "var_care_weight": 0.007193921635962238,
    "avg_forage_weight": 0.9477864808743148,
    "avg_self_weight": 0.5474653754942981,
    "avg_generation": 35.87096774193548,
    "max_generation": 37,
    "n_mothers": 31
  },
  {
    "tick": 4000,
    "avg_care_weight": 0.8130654681839415,
    "var_care_weight": 0.007619193022164368,
    "avg_forage_weight": 0.9458825337679153,
    "avg_self_weight": 0.5511419447747911,
    "avg_generation": 37.935483870967744,
    "max_generation": 39,
    "n_mothers": 31
  },
  {
    "tick": 4200,
    "avg_care_weight": 0.8173419498863677,
    "var_care_weight": 0.007979000800553273,
    "avg_forage_weight": 0.93817423835489,
    "avg_self_weight": 0.5433441416041653,
    "avg_generation": 39.93333333333333,
    "max_generation": 41,
    "n_mothers": 30
  },
  {
    "tick": 4400,
    "avg_care_weight": 0.8245555844293687,
    "var_care_weight": 0.007724935755281904,
    "avg_forage_weight": 0.9329070666687187,
    "avg_self_weight": 0.5380159832862172,
    "avg_generation": 41.96551724137931,
    "max_generation": 43,
    "n_mothers": 29
  },
  {
    "tick": 4600,
    "avg_care_weight": 0.8205888608238691,
    "var_care_weight": 0.006830329850080103,
    "avg_forage_weight": 0.933302506281237,
    "avg_self_weight": 0.5462728772827761,
    "avg_generation": 43.93333333333333,
    "max_generation": 45,
    "n_mothers": 30
  },
  {
    "tick": 4800,
    "avg_care_weight": 0.8265589487188029,
    "var_care_weight": 0.007866995018737905,
    "avg_forage_weight": 0.9297801311139169,
    "avg_self_weight": 0.5431367350620407,
    "avg_generation": 45.90625,
    "max_generation": 47,
    "n_mothers": 32
  },
  {
    "tick": 5000,
    "avg_care_weight": 0.8239558677417088,
    "var_care_weight": 0.008252490679138488,
    "avg_forage_weight": 0.9314148232280375,
    "avg_self_weight": 0.5373877633940137,
    "avg_generation": 48.0,
    "max_generation": 49,
    "n_mothers": 30
  },
  {
    "tick": 5200,
    "avg_care_weight": 0.82530002529846,
    "var_care_weight": 0.0080093395173123,
    "avg_forage_weight": 0.9323870058899708,
    "avg_self_weight": 0.5337648107620873,
    "avg_generation": 50.0,
    "max_generation": 51,
    "n_mothers": 30
  },
  {
    "tick": 5400,
    "avg_care_weight": 0.8187423132404452,
    "var_care_weight": 0.007883091421123305,
    "avg_forage_weight": 0.9300523431134179,
    "avg_self_weight": 0.5364431235748629,
    "avg_generation": 52.0,
    "max_generation": 53,
    "n_mothers": 30
  },
  {
    "tick": 5600,
    "avg_care_weight": 0.8149283217524603,
    "var_care_weight": 0.008747092696699326,
    "avg_forage_weight": 0.9297885971082356,
    "avg_self_weight": 0.5507526318944012,
    "avg_generation": 53.875,
    "max_generation": 55,
    "n_mothers": 32
  },
  {
    "tick": 5800,
    "avg_care_weight": 0.8239867050044075,
    "var_care_weight": 0.008014562797210108,
    "avg_forage_weight": 0.9126078015032184,
    "avg_self_weight": 0.5406031422699888,
    "avg_generation": 56.0,
    "max_generation": 57,
    "n_mothers": 30
  },
  {
    "tick": 6000,
    "avg_care_weight": 0.8259141741207431,
    "var_care_weight": 0.011088244627752214,
    "avg_forage_weight": 0.9148666645692354,
    "avg_self_weight": 0.5595691217890787,
    "avg_generation": 57.935483870967744,
    "max_generation": 59,
    "n_mothers": 31
  },
  {
    "tick": 6200,
    "avg_care_weight": 0.8248757505131917,
    "var_care_weight": 0.011283420544048245,
    "avg_forage_weight": 0.9220352623081278,
    "avg_self_weight": 0.5562761148407385,
    "avg_generation": 59.935483870967744,
    "max_generation": 61,
    "n_mothers": 31
  },
  {
    "tick": 6400,
    "avg_care_weight": 0.8231724199897837,
    "var_care_weight": 0.011488556484279088,
    "avg_forage_weight": 0.9215639345934173,
    "avg_self_weight": 0.5670384276035073,
    "avg_generation": 61.935483870967744,
    "max_generation": 63,
    "n_mothers": 31
  },
  {
    "tick": 6600,
    "avg_care_weight": 0.8340539864012365,
    "var_care_weight": 0.011934457234692138,
    "avg_forage_weight": 0.9200050861284936,
    "avg_self_weight": 0.5642769845240565,
    "avg_generation": 63.93333333333333,
    "max_generation": 65,
    "n_mothers": 30
  },
  {
    "tick": 6800,
    "avg_care_weight": 0.8367379125169959,
    "var_care_weight": 0.012494819946791172,
    "avg_forage_weight": 0.9199831777189675,
    "avg_self_weight": 0.57661841689567,
    "avg_generation": 65.93548387096774,
    "max_generation": 67,
    "n_mothers": 31
  },
  {
    "tick": 7000,
    "avg_care_weight": 0.8445379654928202,
    "var_care_weight": 0.012510856188047138,
    "avg_forage_weight": 0.9121359452720806,
    "avg_self_weight": 0.5742781744773185,
    "avg_generation": 67.93548387096774,
    "max_generation": 69,
    "n_mothers": 31
  },
  {
    "tick": 7200,
    "avg_care_weight": 0.8454108909417415,
    "var_care_weight": 0.012880123757360815,
    "avg_forage_weight": 0.9094082670983633,
    "avg_self_weight": 0.5684743845581653,
    "avg_generation": 69.93548387096774,
    "max_generation": 71,
    "n_mothers": 31
  },
  {
    "tick": 7400,
    "avg_care_weight": 0.8486651811131563,
    "var_care_weight": 0.01268799684280204,
    "avg_forage_weight": 0.899602774337458,
    "avg_self_weight": 0.5728691695764236,
    "avg_generation": 71.93548387096774,
    "max_generation": 73,
    "n_mothers": 31
  },
  {
    "tick": 7600,
    "avg_care_weight": 0.8500489342233493,
    "var_care_weight": 0.01306364371163341,
    "avg_forage_weight": 0.9008838702026819,
    "avg_self_weight": 0.5695551249949028,
    "avg_generation": 73.93333333333334,
    "max_generation": 75,
    "n_mothers": 30
  },
  {
    "tick": 7800,
    "avg_care_weight": 0.858047286004737,
    "var_care_weight": 0.012804690304034534,
    "avg_forage_weight": 0.8950300821508156,
    "avg_self_weight": 0.5819589047453242,
    "avg_generation": 75.93548387096774,
    "max_generation": 77,
    "n_mothers": 31
  },
  {
    "tick": 8000,
    "avg_care_weight": 0.8612298450622001,
    "var_care_weight": 0.01278128012443582,
    "avg_forage_weight": 0.8928746319376281,
    "avg_self_weight": 0.581424379493018,
    "avg_generation": 77.93548387096774,
    "max_generation": 79,
    "n_mothers": 31
  },
  {
    "tick": 8200,
    "avg_care_weight": 0.8661346878538787,
    "var_care_weight": 0.01092292085502993,
    "avg_forage_weight": 0.8899979522113465,
    "avg_self_weight": 0.5789014013469196,
    "avg_generation": 79.93548387096774,
    "max_generation": 81,
    "n_mothers": 31
  },
  {
    "tick": 8400,
    "avg_care_weight": 0.8575635835815015,
    "var_care_weight": 0.012592702586710351,
    "avg_forage_weight": 0.8845186386696781,
    "avg_self_weight": 0.5771832503312863,
    "avg_generation": 81.93548387096774,
    "max_generation": 83,
    "n_mothers": 31
  },
  {
    "tick": 8600,
    "avg_care_weight": 0.857199097648497,
    "var_care_weight": 0.012116272874266866,
    "avg_forage_weight": 0.873098782939183,
    "avg_self_weight": 0.5782264707669458,
    "avg_generation": 83.93548387096774,
    "max_generation": 85,
    "n_mothers": 31
  },
  {
    "tick": 8800,
    "avg_care_weight": 0.8566721025173273,
    "var_care_weight": 0.013398749660674987,
    "avg_forage_weight": 0.88105476435287,
    "avg_self_weight": 0.5869528592318983,
    "avg_generation": 85.96666666666667,
    "max_generation": 87,
    "n_mothers": 30
  },
  {
    "tick": 9000,
    "avg_care_weight": 0.8463129774826541,
    "var_care_weight": 0.011407529118814047,
    "avg_forage_weight": 0.8787638936209669,
    "avg_self_weight": 0.580137286789655,
    "avg_generation": 87.93548387096774,
    "max_generation": 89,
    "n_mothers": 31
  },
  {
    "tick": 9200,
    "avg_care_weight": 0.8476360956966238,
    "var_care_weight": 0.011433725434772684,
    "avg_forage_weight": 0.8791746465132114,
    "avg_self_weight": 0.581525271851052,
    "avg_generation": 89.93548387096774,
    "max_generation": 91,
    "n_mothers": 31
  },
  {
    "tick": 9400,
    "avg_care_weight": 0.8442534598998439,
    "var_care_weight": 0.011389156162541549,
    "avg_forage_weight": 0.8791746465132114,
    "avg_self_weight": 0.5742044363889519,
    "avg_generation": 91.93548387096774,
    "max_generation": 93,
    "n_mothers": 31
  },
  {
    "tick": 9600,
    "avg_care_weight": 0.8311763605204194,
    "var_care_weight": 0.011887696088887035,
    "avg_forage_weight": 0.8818876761380956,
    "avg_self_weight": 0.5708079126045635,
    "avg_generation": 93.93548387096774,
    "max_generation": 95,
    "n_mothers": 31
  },
  {
    "tick": 9800,
    "avg_care_weight": 0.8304751725912816,
    "var_care_weight": 0.011457661541793592,
    "avg_forage_weight": 0.8751464851284291,
    "avg_self_weight": 0.5725218556406918,
    "avg_generation": 95.93548387096774,
    "max_generation": 97,
    "n_mothers": 31
  },
  {
    "tick": 10000,
    "avg_care_weight": 0.8263262703580027,
    "var_care_weight": 0.014915494608655534,
    "avg_forage_weight": 0.8801318339713342,
    "avg_self_weight": 0.5795295671363513,
    "avg_generation": 97.93548387096774,
    "max_generation": 99,
    "n_mothers": 31
  }
]